core/__init__.py
core/log.py
core/option.py
core/pynodb.py
core/setting.py
core/start.py
core/store.py
test/__init__.py
test/basetest.py
test/pressuretest.py
landb_dbld-0.0.1.dist-info/LICENSE
landb_dbld-0.0.1.dist-info/METADATA
landb_dbld-0.0.1.dist-info/WHEEL
landb_dbld-0.0.1.dist-info/top_level.txt
landb_dbld-0.0.1.dist-info/RECORD
