Metadata-Version: 2.1
Name: landb-dbld
Version: 0.0.1
Summary: 一个python数据库
Home-page: UNKNOWN
Author: zhang
Author-email: 2426398674@qq.com
License: UNKNOWN
Platform: UNKNOWN
Classifier: Programming Language :: Python :: 3
Classifier: License :: OSI Approved :: MIT License
Classifier: Operating System :: OS Independent
Requires-Python: >=3.7
